trankit/__init__.py
trankit/__main__.py
trankit/config.py
trankit/copy_saved_models.py
trankit/pipeline.py
trankit/tpipeline.py
trankit/iterators/__init__.py
trankit/iterators/lemmatizer_iterators.py
trankit/iterators/mwt_iterators.py
trankit/iterators/ner_iterators.py
trankit/iterators/tagger_iterators.py
trankit/iterators/tokenizer_iterators.py
trankit/models/__init__.py
trankit/models/base_models.py
trankit/models/classifiers.py
trankit/models/crf_model.py
trankit/models/lemma_model.py
trankit/models/mwt_model.py
trankit/models/seq2seq_model.py
trankit/utils/__init__.py
trankit/utils/base_utils.py
trankit/utils/chuliu_edmonds.py
trankit/utils/conll.py
trankit/utils/conll18_ud_eval.py
trankit/utils/mwt_utils.py
trankit/utils/ner_utils.py
trankit/utils/seq2seq_utils.py
trankit/utils/seq2seq_vocabs.py
trankit/utils/tagger_utils.py
trankit/utils/tbinfo.py
trankit/utils/tokenizer_utils.py
trankit_beta-0.2.0.dist-info/LICENSE
trankit_beta-0.2.0.dist-info/METADATA
trankit_beta-0.2.0.dist-info/WHEEL
trankit_beta-0.2.0.dist-info/top_level.txt
trankit_beta-0.2.0.dist-info/RECORD
